{"name":"man","desc":"man 命令行用于显示 Linux 上的命令的手册页。通过 man，用户可以了解命令的用法、参数和选项等信息。","usages":[{"form":{"":{"name":"命令名称","required":true,"type":"string"},"-a":{"type":"check","name":"显示所有页面","optionName":"-a"},"-C":{"type":"check","name":"将带有 ANSI 转义代码的输出以纯文本形式显示","optionName":"-C"},"-D":{"type":"check","name":"打印出 man 将使用的宏定义","optionName":"-D"},"-f":{"type":"check","name":"等价于 whatis 命令","optionName":"-f"},"-F":{"type":"check","name":"等价于 whatis 命令，但忽略字母大小写","optionName":"-F"},"-h":{"type":"check","name":"显示帮助信息","optionName":"-h"},"-k":{"type":"check","name":"等价于 apropos 命令","optionName":"-k"},"-K":{"type":"check","name":"等价于 apropos 命令，但忽略字母大小写","optionName":"-K"},"-l":{"type":"check","name":"将搜索结果逐行打印到终端上","optionName":"-l"},"-L":{"type":"check","name":"将搜索结果逐行打印到终端上，但忽略字母大小写","optionName":"-L"},"-m":{"type":"check","name":"为所有手册页搜索所有的 manpath 目录","optionName":"-m"},"-r":{"type":"check","name":"搜索 manpath 中所有目录，包括子目录","optionName":"-r"},"-w":{"type":"check","name":"不输出结果，只显示手册页的路径","optionName":"-w"},"-d":{"type":"string","name":"指定 manpath 目录，man 将在该目录中查找手册页","optionName":"-d"},"-M":{"type":"string","name":"类似于 -m 选项，但只搜索制定的 manpath 目录","optionName":"-M"},"-P":{"type":"string","name":"指定使用的 pager","optionName":"-P"},"-S":{"type":"string","name":"指定搜索的手册节号","optionName":"-S"}}}],"content":"<h2 id=\"例子\">例子</h2>\n<ul>\n<li>显示 <code>ls</code> 命令的手册页：<code>man ls</code></li>\n<li>显示 <code>ls</code> 命令的 <code>NAME</code> 部分：<code>man -f ls</code></li>\n<li>显示所有与 <code>ls</code> 相关的手册页：<code>man -k ls</code></li>\n<li>显示 <code>ls</code> 命令的 <code>DESCRIPTION</code> 部分：<code>man -d ls</code></li>\n<li>显示 <code>ls</code> 命令的 <code>OPTIONS</code> 部分：<code>man -h ls</code></li>\n<li>等价于 <code>whatis</code> 命令：<code>man -f ls</code></li>\n<li>显示手册页的路径：<code>man -w ls</code></li>\n</ul>\n<p>注意：这里的 <code>ls</code> 命令只是一个示例，可以替换为任何其他命令。</p>\n"}