{"name":"umount","desc":"`umount` 命令用于卸载已经挂载的文件系统。","usages":[{"form":{"":{"name":"路径","type":"string"},"-a":{"type":"check","name":"卸载所有已挂载的文件系统","optionName":"-a"},"-c":{"type":"check","name":"立刻中断正在进行的卸载操作","optionName":"-c"},"-h":{"type":"check","name":"显示帮助信息并退出","optionName":"-h"},"-n":{"type":"check","name":"执行卸载操作时不要更新 /etc/mtab 文件","optionName":"-n"},"-r":{"type":"check","name":"以只读方式挂载文件系统","optionName":"-r"},"-t":{"type":"string","name":"指定文件系统类型","optionName":"-t"},"--no-canonicalize":{"type":"check","name":"不将挂载点路径转换为真实路径","optionName":"--no-canonicalize"},"--no-sync":{"type":"check","name":"以异步方式卸载文件系统","optionName":"--no-sync"},"--version":{"type":"check","name":"显示版本信息并退出","optionName":"--version"}}}],"content":"<h2 id=\"例子\">例子</h2>\n<h3 id=\"卸载一个文件系统\">卸载一个文件系统</h3>\n<pre><code class=\"language-vb.net\">umount /mnt\n</code></pre>\n<h3 id=\"卸载所有已挂载的文件系统\">卸载所有已挂载的文件系统</h3>\n<pre><code class=\"language-vb.net\">umount -a\n</code></pre>\n<h3 id=\"卸载一个特定的文件系统类型\">卸载一个特定的文件系统类型</h3>\n<pre><code class=\"language-vb.net\">umount -t ext4 /mnt\n</code></pre>\n<h3 id=\"以只读方式卸载文件系统\">以只读方式卸载文件系统</h3>\n<pre><code class=\"language-vb.net\">umount -r /mnt\n</code></pre>\n"}