{"name":"vmstat","desc":"vmstat 命令行可用于报告系统的虚拟内存统计信息，包括 CPU 利用率、内存使用情况和虚拟内存交换状态等。","usages":[{"form":{"-a":{"type":"check","name":"显示活跃和非活跃内存的使用情况","optionName":"-a"},"-f":{"type":"check","name":"显示自由页的数量","optionName":"-f"},"-m":{"type":"check","name":"显示内存的使用情况","optionName":"-m"},"-n":{"type":"string","name":"在两次显示间的等待时间（单位：秒）","optionName":"-n"},"-s":{"type":"check","name":"显示系统统计信息的摘要","optionName":"-s"}}}],"content":"<h2 id=\"例子\">例子</h2>\n<ul>\n<li><code>vmstat</code>: 显示在系统启动之后的虚拟内存使用情况。</li>\n<li><code>vmstat 5</code>: 每 5 秒钟显示一次虚拟内存使用情况。</li>\n<li><code>vmstat -a</code>: 显示活跃和非活跃内存的使用情况。</li>\n<li><code>vmstat -f</code>: 显示自由页的数量。</li>\n<li><code>vmstat -m</code>: 显示内存的使用情况。</li>\n<li><code>vmstat -n 5</code>: 每 5 秒钟显示一次虚拟内存使用情况，并在两次显示之间等待 5 秒钟。</li>\n</ul>\n"}