{"name":"uniq","desc":"The `uniq` command removes duplicate lines from a sorted file. It can be customized using various options, such as the `-c` option to count the number of occurrences of each repeated line.","usages":[{"form":{"":{"name":"file path","required":true,"type":"string"},"-c":{"type":"check","name":"count the number of occurrences of each repeated line","optionName":"-c"},"-d":{"type":"check","name":"only display duplicated lines","optionName":"-d"},"-f":{"type":"string","name":"ignore the first N fields in each line","optionName":"-f"},"-i":{"type":"check","name":"ignore case differences","optionName":"-i"},"-s":{"type":"string","name":"only compare the first N characters in each line","optionName":"-s"},"-u":{"type":"check","name":"only display unique lines","optionName":"-u"}}}],"content":"<h2 id=\"examples\">Examples</h2>\n<ul>\n<li>Remove duplicate lines from a sorted file: <code>uniq file.txt</code></li>\n<li>Count the number of occurrences of each repeated line: <code>uniq -c file.txt</code></li>\n<li>Only display duplicated lines: <code>uniq -d file.txt</code></li>\n<li>Ignore the first N fields in each line: <code>uniq -f N file.txt</code></li>\n<li>Ignore case differences: <code>uniq -i file.txt</code></li>\n<li>Only compare the first N characters in each line: <code>uniq -s N file.txt</code></li>\n<li>Only display unique lines: <code>uniq -u file.txt</code></li>\n</ul>\n<p>Note: The <code>uniq</code> command only removes duplicate lines from a sorted file. If the file is not sorted, you need to use the <code>sort</code> command to sort the file first, for example, <code>sort file.txt | uniq</code>.</p>\n"}