{"name":"wget","desc":"wget is a command-line tool used for downloading files from the internet. It can download a single file or an entire website, and supports resuming downloads.","usages":[{"form":{"":{"name":"Target URL","required":true,"type":"string"},"-c":{"type":"check","name":"Continue the download from where it left off.","optionName":"-c"},"-O, --output-document":{"type":"string","name":"Write documents to file.","optionName":"-O, --output-document"},"-i, --input-file":{"type":"string","name":"Read URL from file.","optionName":"-i, --input-file"},"-b":{"type":"check","name":"Go to background immediately after startup.","optionName":"-b"},"-e":{"type":"string","name":"Execute command.","optionName":"-e"},"-S, --server-response":{"type":"check","name":"Print the server's response.","optionName":"-S, --server-response"},"-U, --user-agent":{"type":"string","name":"Identify as agent-string to server.","optionName":"-U, --user-agent"},"-q":{"type":"check","name":"Quiet mode.","optionName":"-q"},"-t":{"type":"string","name":"Set number of retries.","optionName":"-t"},"-w":{"type":"string","name":"Wait SECONDS between retrievals.","optionName":"-w"},"-V":{"type":"check","name":"Version information.","optionName":"-V"},"-h":{"type":"check","name":"Help information.","optionName":"-h"},"--mirror":{"type":"check","name":"Mirror site's directory structure.","optionName":"--mirror"},"-p, --page-requisites":{"type":"check","name":"Get all images, etc. needed to display HTML page.","optionName":"-p, --page-requisites"},"--convert-links":{"type":"check","name":"Convert links to local files.","optionName":"--convert-links"},"-P, --directory-prefix":{"type":"string","name":"Save files to PREFIX/...","optionName":"-P, --directory-prefix"}}}],"content":"<h2 id=\"examples\">Examples</h2>\n<ul>\n<li>Download a single file: <code>wget &lt;https://example.com/file.zip</code>&gt;</li>\n<li>Download an entire website: <code>wget --mirror -p --convert-links -P ./LOCAL-DIR WEBSITE-URL</code></li>\n<li>Resume a download: <code>wget -c &lt;https://example.com/file.zip</code>&gt;</li>\n<li>Download using a proxy server: <code>wget -e use_proxy=yes -e http_proxy=PROXY-URL &lt;https://example.com/file.zip</code>&gt;</li>\n<li>Limit download speed: <code>wget --limit-rate=200k &lt;https://example.com/file.zip</code>&gt;</li>\n<li>Set the user agent: <code>wget --user-agent=&quot;Mozilla/5.0 (Windows NT 10.0; Win64; x64) AppleWebKit/537.36 (KHTML, like Gecko) Chrome/58.0.3029.110 Safari/537.3&quot; &lt;https://example.com/file.zip</code>&gt;</li>\n</ul>\n"}